mlrpc/__init__.py
mlrpc/cfg.py
mlrpc/cli.py
mlrpc/client.py
mlrpc/deployment.py
mlrpc/detect.py
mlrpc/flavor.py
mlrpc/hotreload.py
mlrpc/proto.py
mlrpc/proxy.py
mlrpc/utils.py
mlrpc-0.11.0.dist-info/LICENSE
mlrpc-0.11.0.dist-info/METADATA
mlrpc-0.11.0.dist-info/WHEEL
mlrpc-0.11.0.dist-info/entry_points.txt
mlrpc-0.11.0.dist-info/top_level.txt
mlrpc-0.11.0.dist-info/RECORD
