Metadata-Version: 2.1
Name: mlrpc
Version: 0.11.0
Summary: Deploy FastAPI applications on MLFlow
Home-page: https://github.com/stikkireddy/mlflow-rpc
Author: Sri Tikkireddy
Author-email: sri.tikkireddy@databricks.com
Classifier: Programming Language :: Python :: 3
Classifier: License :: OSI Approved :: MIT License
Classifier: Operating System :: OS Independent
Requires-Python: >=3.10
License-File: LICENSE
Provides-Extra: cli
Requires-Dist: pathspec ; extra == 'cli'
Requires-Dist: mlflow-skinny[databricks] ; extra == 'cli'
Requires-Dist: scipy ; extra == 'cli'
Requires-Dist: fastapi ; extra == 'cli'
Requires-Dist: pandas ; extra == 'cli'
Requires-Dist: httpx ; extra == 'cli'
Requires-Dist: databricks-sdk ; extra == 'cli'
Requires-Dist: click ; extra == 'cli'
Requires-Dist: click-configfile ; extra == 'cli'
Requires-Dist: python-dotenv ; extra == 'cli'
Requires-Dist: uvicorn ; extra == 'cli'
Requires-Dist: virtualenv ; extra == 'cli'
Requires-Dist: flask ; extra == 'cli'
Requires-Dist: watchdog ; extra == 'cli'
Requires-Dist: detect-secrets ; extra == 'cli'
Provides-Extra: client
Requires-Dist: databricks-sdk ; extra == 'client'
